pytest_railflow_testrail_reporter/__init__.py
pytest_railflow_testrail_reporter/plugin.py
pytest_railflow_testrail_reporter-0.2.5.dist-info/LICENSE
pytest_railflow_testrail_reporter-0.2.5.dist-info/METADATA
pytest_railflow_testrail_reporter-0.2.5.dist-info/WHEEL
pytest_railflow_testrail_reporter-0.2.5.dist-info/entry_points.txt
pytest_railflow_testrail_reporter-0.2.5.dist-info/top_level.txt
pytest_railflow_testrail_reporter-0.2.5.dist-info/RECORD
